{
  "gitSyncId": "682d4004f7a17057bce3c58d_27637cad-3b3f-4961-aa6e-c2e409fa2daa",
  "id": "task2_getSchoolNames",
  "pluginId": "postgres-plugin",
  "pluginType": "DB",
  "unpublishedAction": {
    "actionConfiguration": {
      "body": "SELECT DISTINCT school_name FROM public.student_data ORDER BY school_name;",
      "encodeParamsToggle": true,
      "paginationType": "NONE",
      "pluginSpecifiedTemplates": [
        {
          "value": true
        }
      ],
      "timeoutInMillisecond": 10000
    },
    "confirmBeforeExecute": false,
    "datasource": {
      "id": "StudentDb",
      "isAutoGenerated": false,
      "name": "StudentDb",
      "pluginId": "postgres-plugin"
    },
    "dynamicBindingPathList": [],
    "name": "getSchoolNames",
    "pageId": "task2",
    "runBehaviour": "MANUAL",
    "userSetOnLoad": true
  }
}